eth_signer/__init__.py
eth_signer/py.typed
eth_signer/signer.py
eth_signer/utils/__init__.py
eth_signer/utils/ecdsa.py
eth_signer-0.1.10.dist-info/LICENSE
eth_signer-0.1.10.dist-info/METADATA
eth_signer-0.1.10.dist-info/WHEEL
eth_signer-0.1.10.dist-info/top_level.txt
eth_signer-0.1.10.dist-info/RECORD
