Metadata-Version: 2.1
Name: eth-signer
Version: 0.1.10
Summary: A Python library for transection signing using AWS Key Management Service.
Home-page: https://github.com/sejpalkalpesh/eth-signer
Author: Kalpesh Sejpal
Author-email: sejpalkalpesh@gmail.com
License: MIT
Keywords: ethereum AWS KMS,
Platform: UNKNOWN
Classifier: Development Status :: 3 - Alpha
Classifier: Intended Audience :: Developers
Classifier: License :: OSI Approved :: MIT License
Classifier: Natural Language :: English
Classifier: Programming Language :: Python :: 3
Classifier: Programming Language :: Python :: 3.6
Classifier: Programming Language :: Python :: 3.7
Classifier: Programming Language :: Python :: 3.8
Classifier: Programming Language :: Python :: 3.9
Requires-Python: >=3.6,<4
Requires-Dist: boto3 (<1.19.0,>=1.18.42)
Requires-Dist: eth-account (>=0.5.5)
Requires-Dist: pycryptodome (<4,>=3.6.6)
Provides-Extra: dev
Requires-Dist: Sphinx (<2,>=1.6.5) ; extra == 'dev'
Requires-Dist: bumpversion (==0.5.3) ; extra == 'dev'
Requires-Dist: flake8 (==3.8.3) ; extra == 'dev'
Requires-Dist: isort (<4.3.5,>=4.2.15) ; extra == 'dev'
Requires-Dist: mypy (==0.812) ; extra == 'dev'
Requires-Dist: pytest (==5.4.1) ; extra == 'dev'
Requires-Dist: setuptools (>=38.6.0) ; extra == 'dev'
Requires-Dist: sphinx-rtd-theme (<2,>=0.1.9) ; extra == 'dev'
Requires-Dist: towncrier (<20,>=19.2.0) ; extra == 'dev'
Requires-Dist: tox (>=1.8.0) ; extra == 'dev'
Requires-Dist: twine (<2,>=1.13) ; extra == 'dev'
Provides-Extra: docs
Requires-Dist: Sphinx (<2,>=1.6.5) ; extra == 'docs'
Requires-Dist: sphinx-rtd-theme (<2,>=0.1.9) ; extra == 'docs'
Requires-Dist: towncrier (<20,>=19.2.0) ; extra == 'docs'
Provides-Extra: eth-signer
Requires-Dist: boto3 (<1.19.0,>=1.18.42) ; extra == 'eth-signer'
Requires-Dist: eth-account (>=0.5.5) ; extra == 'eth-signer'
Requires-Dist: pycryptodome (<4,>=3.6.6) ; extra == 'eth-signer'
Provides-Extra: lint
Requires-Dist: flake8 (==3.8.3) ; extra == 'lint'
Requires-Dist: isort (<4.3.5,>=4.2.15) ; extra == 'lint'
Requires-Dist: mypy (==0.812) ; extra == 'lint'
Provides-Extra: test
Requires-Dist: pytest (==5.4.1) ; extra == 'test'
